ClockParts/__init__.py
ClockParts/shaft.py
ClockParts/utils/main.py
clockparts-0.1.56.dist-info/LICENSE
clockparts-0.1.56.dist-info/METADATA
clockparts-0.1.56.dist-info/WHEEL
clockparts-0.1.56.dist-info/RECORD
