Metadata-Version: 2.1
Name: ClockParts
Version: 0.1.56
Summary: Dynamic task scheduler
Home-page: https://github.com/ASCII000/clock-parts
Author: Emerson Silva
Requires-Python: >=3.11
Classifier: Programming Language :: Python :: 3
Classifier: Programming Language :: Python :: 3.11
Classifier: Programming Language :: Python :: 3.12
Classifier: Programming Language :: Python :: 3.13
Requires-Dist: colorama (>=0.4.6,<0.5.0)
Requires-Dist: psutil (>=6.1.0,<7.0.0)
Project-URL: Repository, https://github.com/ASCII000/clock-parts
